main.py
README.md
utils.py
devgossip_praiseey-0.1.4.dist-info/entry_points.txt
devgossip_praiseey-0.1.4.dist-info/WHEEL
devgossip_praiseey-0.1.4.dist-info/METADATA
devgossip_praiseey-0.1.4.dist-info/RECORD
