Metadata-Version: 2.1
Name: devgossip-praiseey
Version: 0.1.4
Summary: A platform for developers to gossip about any topic. To install: pip install devgossip==0.1.4. To run: dev-gossip
License: MIT
Author: Your Name
Author-email: you@example.com
Requires-Python: >=3.0,<4.0
Classifier: License :: OSI Approved :: MIT License
Classifier: Programming Language :: Python :: 3
Classifier: Programming Language :: Python :: 3.4
Classifier: Programming Language :: Python :: 3.5
Classifier: Programming Language :: Python :: 3.6
Classifier: Programming Language :: Python :: 3.7
Classifier: Programming Language :: Python :: 3.8
